extradict/__init__.py
extradict/binary_tree_dict.py
extradict/blobdict.py
extradict/extratuple.py
extradict/grouper.py
extradict/map_getter.py
extradict/misc.py
extradict/nested_data.py
extradict/normalized_dict.py
extradict/reciprocal_dict.py
extradict/trie.py
extradict/version_dict.py
extradict-0.7.0.dist-info/licenses/COPYING
extradict-0.7.0.dist-info/licenses/LICENSE
extradict-0.7.0.dist-info/METADATA
extradict-0.7.0.dist-info/WHEEL
extradict-0.7.0.dist-info/top_level.txt
extradict-0.7.0.dist-info/RECORD
