Metadata-Version: 2.4
Name: extradict
Version: 0.7.0
Summary: Miscelaneous data containers and utilities: A versioned dictionary, a bidirectional dictionary, a binary tree backed dictionary, a Grouper iterator mapper similar to itertools.tee, and an easy extractor from dictionary key/values to variables
Author: Joao S. O. Bueno
Project-URL: repository, https://github.com/jsbueno/extradict
Keywords: versioned,bijective,assigner,getter,unpack,transactional,container,collection,dict,dictionary,normalized,binarytree,trie
Classifier: Development Status :: 5 - Production/Stable
Classifier: Intended Audience :: Developers
Classifier: Programming Language :: Python :: 3.8
Classifier: Programming Language :: Python :: 3.9
Classifier: Programming Language :: Python :: 3.10
Classifier: Programming Language :: Python :: 3.11
Classifier: Programming Language :: Python :: 3.12
Classifier: Programming Language :: Python :: 3.13
Classifier: Programming Language :: Python :: Implementation :: CPython
Classifier: Programming Language :: Python :: Implementation :: PyPy
Classifier: License :: OSI Approved :: GNU Lesser General Public License v3 or later (LGPLv3+)
Classifier: Operating System :: OS Independent
Requires-Python: >=3.8
License-File: LICENSE
License-File: COPYING
Provides-Extra: dev
Requires-Dist: pytest; extra == "dev"
Requires-Dist: black; extra == "dev"
Requires-Dist: pytest-coverage; extra == "dev"
Dynamic: license-file
